<annotation>
	<folder>S4</folder>
	<filename>20230505_105414.jpg</filename>
	<path>D:\QR_Dataset\train\S4\20230505_105414.jpg</path>
	<source>
		<database>Unknown</database>
	</source>
	<size>
		<width>2560</width>
		<height>1440</height>
		<depth>3</depth>
	</size>
	<segmented>0</segmented>
	<object>
		<name>S4</name>
		<pose>Unspecified</pose>
		<truncated>0</truncated>
		<difficult>0</difficult>
		<bndbox>
			<xmin>1133</xmin>
			<ymin>421</ymin>
			<xmax>1440</xmax>
			<ymax>722</ymax>
		</bndbox>
	</object>
</annotation>
